api_scene/__init__.py
api_scene/classes/__init__.py
api_scene/classes/download.py
api_scene/classes/lan.py
api_scene/classes/movie.py
api_scene/classes/search.py
api_scene/classes/sub.py
api_scene/classes/tv.py
api_scene/classes/utils.py
api_scene-1.0.0.dist-info/LICENSE
api_scene-1.0.0.dist-info/METADATA
api_scene-1.0.0.dist-info/WHEEL
api_scene-1.0.0.dist-info/top_level.txt
api_scene-1.0.0.dist-info/RECORD
